README.md
setup.py
superapipy/__init__.py
superapipy/superapipy.py
superapipy.egg-info/PKG-INFO
superapipy.egg-info/SOURCES.txt
superapipy.egg-info/dependency_links.txt
superapipy.egg-info/top_level.txt