Metadata-Version: 2.1
Name: superapipy
Version: 0.0.0
Summary: A ai package
Home-page: https://github.com/pypa/sampleproject
Author: Vihaan Pundir
Author-email: vihaan.pundir26@gmail.com
License: UNKNOWN
Platform: UNKNOWN
Classifier: Programming Language :: Python :: 3
Classifier: License :: OSI Approved :: MIT License
Classifier: Operating System :: OS Independent
Requires-Python: >=3.8.5
